{
  "data": [
    {
      "id": "1",
      "ciudad": "Lima",
      "alcalde": "Miguel Romero Sotelo",
      "habitantes": 9943800
    },
    {
      "id": "2",
      "ciudad": "Arequipa",
      "alcalde": "Omar Julio Candia Aguilar",
      "habitantes": 1142900
    },
    {
      "id": "3",
      "ciudad": "Trujillo",
      "alcalde": "Daniel Marcelo Jacinto",
      "habitantes": 1088300
    },
    {
      "id": "4",
      "ciudad": "Cusco",
      "alcalde": "Víctor G. Boluarte Medina",
      "habitantes": 437538
    },
    {
      "id": "5",
      "ciudad": "Chiclayo",
      "alcalde": "Marcos Gasco Arrobas",
      "habitantes": 562508
    },
    {
      "id": "6",
      "ciudad": "Huaraz",
      "alcalde": "Cesar Martin Bustamante Flores",
      "habitantes": 123069
    },
    {
      "id": "7",
      "ciudad": "Huancayo",
      "alcalde": "Juan Carlos Quispe Ledesma",
      "habitantes": 400271
    },
    {
      "id": "8",
      "ciudad": "Ayacucho",
      "alcalde": "Yuri Alberto Gutiérrez Gutiérrez",
      "habitantes": 228427
    },
    {
      "id": "9",
      "ciudad": "Iquitos",
      "alcalde": "Francisco Sanjurjo Dávila",
      "habitantes": 163502
    },
    {
      "id": "10",
      "ciudad": "Piura",
      "alcalde": "Juan Díaz Dios",
      "habitantes": 560345
    }
  ]
}
